{
    "asset": {
        "format": "jpg",
        "id": "1ef34dd89792d5b46c8c3f6ff5691311",
        "name": "814af737-1fe5-4831-85a4-bf22801170fc.jpg",
        "path": "file:C:/Users/hnm08/PycharmProjects/crawlImageFromGGImg/rawImg/814af737-1fe5-4831-85a4-bf22801170fc.jpg",
        "size": {
            "width": 600,
            "height": 400
        },
        "state": 2,
        "type": 1
    },
    "regions": [
        {
            "id": "0NQn2LwTW",
            "type": "RECTANGLE",
            "tags": [
                "top_left"
            ],
            "boundingBox": {
                "height": 19.36560934891486,
                "width": 21.380846325167038,
                "left": 88.19599109131403,
                "top": 71.68196994991652
            },
            "points": [
                {
                    "x": 88.19599109131403,
                    "y": 71.68196994991652
                },
                {
                    "x": 109.57683741648107,
                    "y": 71.68196994991652
                },
                {
                    "x": 109.57683741648107,
                    "y": 91.04757929883138
                },
                {
                    "x": 88.19599109131403,
                    "y": 91.04757929883138
                }
            ]
        },
        {
            "id": "jljDJFv6a",
            "type": "RECTANGLE",
            "tags": [
                "top_right"
            ],
            "boundingBox": {
                "height": 19.36560934891486,
                "width": 20.044543429844097,
                "left": 465.03340757238306,
                "top": 73.68530884808013
            },
            "points": [
                {
                    "x": 465.03340757238306,
                    "y": 73.68530884808013
                },
                {
                    "x": 485.07795100222717,
                    "y": 73.68530884808013
                },
                {
                    "x": 485.07795100222717,
                    "y": 93.05091819699499
                },
                {
                    "x": 465.03340757238306,
                    "y": 93.05091819699499
                }
            ]
        },
        {
            "id": "YyCgOK3kt",
            "type": "RECTANGLE",
            "tags": [
                "bottom_right"
            ],
            "boundingBox": {
                "height": 22.70450751252087,
                "width": 20.71269487750557,
                "left": 461.0244988864143,
                "top": 306.07262103505843
            },
            "points": [
                {
                    "x": 461.0244988864143,
                    "y": 306.07262103505843
                },
                {
                    "x": 481.73719376391983,
                    "y": 306.07262103505843
                },
                {
                    "x": 481.73719376391983,
                    "y": 328.7771285475793
                },
                {
                    "x": 461.0244988864143,
                    "y": 328.7771285475793
                }
            ]
        },
        {
            "id": "6O3pQepOM",
            "type": "RECTANGLE",
            "tags": [
                "bottom_left"
            ],
            "boundingBox": {
                "height": 20.70116861435726,
                "width": 20.044543429844097,
                "left": 85.52338530066815,
                "top": 306.7404006677796
            },
            "points": [
                {
                    "x": 85.52338530066815,
                    "y": 306.7404006677796
                },
                {
                    "x": 105.56792873051225,
                    "y": 306.7404006677796
                },
                {
                    "x": 105.56792873051225,
                    "y": 327.44156928213687
                },
                {
                    "x": 85.52338530066815,
                    "y": 327.44156928213687
                }
            ]
        }
    ],
    "version": "2.2.0"
}